README.md
setup.py
pangu_task/__init__.py
pangu_task/route.py
pangu_task/task.py
pangu_task.egg-info/PKG-INFO
pangu_task.egg-info/SOURCES.txt
pangu_task.egg-info/dependency_links.txt
pangu_task.egg-info/top_level.txt